wlosd/__init__.py
wlosd/__main__.py
wlosd/version.py
wlosd/wlosd.py
wlosd-1.1.1.dist-info/licenses/LICENSE
wlosd-1.1.1.dist-info/METADATA
wlosd-1.1.1.dist-info/WHEEL
wlosd-1.1.1.dist-info/entry_points.txt
wlosd-1.1.1.dist-info/top_level.txt
wlosd-1.1.1.dist-info/RECORD
